MANIFEST.in
README.rst
setup.py
magento_models.egg-info/PKG-INFO
magento_models.egg-info/SOURCES.txt
magento_models.egg-info/dependency_links.txt
magento_models.egg-info/not-zip-safe
magento_models.egg-info/requires.txt
magento_models.egg-info/top_level.txt
mm/__init__.py
mm/db.py
mm/exceptions.py
mm/config/__init__.py
mm/config/db.py
mm/resources/README.rst
mm/resources/requirements.txt
mm/routines/__init__.py
mm/routines/attributes.py
mm/routines/category.py
mm/routines/inventory.py
mm/routines/media.py
mm/routines/product.py
mm/routines/sales.py
mm/routines/website.py