Metadata-Version: 1.0
Name: magento-models
Version: 0.2.1
Summary: Magento DB routine interfaces
Home-page: https://github.com/CoffeeForThinkers/MagentoModels
Author: Dustin Oprea
Author-email: dustin@randomingenuity.com
License: GPL3
Platform: UNKNOWN
